dndgmod/__init__.py
dndgmod/__main__.py
dndgmod/assets/new_font_sheet_3_5.png
dndgmod/main.py
dndgmod/subcommands/compile.py
dndgmod/subcommands/create.py
dndgmod/subcommands/cycle.py
dndgmod/subcommands/decompile.py
dndgmod/subcommands/delete.py
dndgmod/subcommands/init.py
dndgmod/subcommands/open.py
dndgmod/subcommands/package.py
dndgmod/subcommands/patch.py
dndgmod/subcommands/revert.py
dndgmod/subcommands/unpackage.py
dndgmod/subcommands/upgrade.py
dndgmod/templates/card_art_sprite_frames.tres.j2
dndgmod/templates/card_effect_XXX.tres.j2
dndgmod/templates/card_list_entry.j2
dndgmod/templates/CardEffectXXX.gd.j2
dndgmod/templates/on_event.gd.j2
dndgmod/templates/wait_for.gd.j2
dndgmod/util/files.py
dndgmod/util/logger.py
dndgmod/util/progress.py
dndgmod/util/slug.py
dndgmod/util/spritesheet.py
dndgmod-0.4.4.post1.dist-info/entry_points.txt
dndgmod-0.4.4.post1.dist-info/METADATA
dndgmod-0.4.4.post1.dist-info/WHEEL
dndgmod-0.4.4.post1.dist-info/RECORD
