Metadata-Version: 2.1
Name: dndgmod
Version: 0.4.4.post1
Summary: A Dungeons & Degenerate Gamblers Modloader
Home-page: https://github.com/TotallyNotSethP/DnDGMod
License: GPL-3.0-or-later
Keywords: modding
Author: Seth Peace
Author-email: sethevanpeace@gmail.com
Requires-Python: >=3.12,<4.0
Classifier: Development Status :: 3 - Alpha
Classifier: Environment :: Console
Classifier: Environment :: Win32 (MS Windows)
Classifier: Intended Audience :: Developers
Classifier: Intended Audience :: End Users/Desktop
Classifier: License :: OSI Approved :: GNU General Public License v3 or later (GPLv3+)
Classifier: Natural Language :: English
Classifier: Operating System :: Microsoft :: Windows :: Windows 10
Classifier: Operating System :: Microsoft :: Windows :: Windows 11
Classifier: Programming Language :: Python :: 3
Classifier: Programming Language :: Python :: 3.12
Classifier: Topic :: Games/Entertainment :: Turn Based Strategy
Classifier: Topic :: Software Development :: Build Tools
Classifier: Topic :: Software Development :: Disassemblers
Requires-Dist: appdirs (>=1.4.4,<2.0.0)
Requires-Dist: boto3 (>=1.34.132,<2.0.0)
Requires-Dist: jinja2 (>=3.1.3,<4.0.0)
Requires-Dist: pillow (>=10.3.0,<11.0.0)
Requires-Dist: pyyaml (>=6.0.1,<7.0.0)
Requires-Dist: typer[all] (>=0.12.3,<0.13.0)
Project-URL: Documentation, https://dndgmod.rtfd.io
Project-URL: Repository, https://github.com/TotallyNotSethP/DnDGMod
